subdo/__init__.py
subdo/subd.py
subdo-0.1.dist-info/METADATA
subdo-0.1.dist-info/WHEEL
subdo-0.1.dist-info/top_level.txt
subdo-0.1.dist-info/RECORD
