Metadata-Version: 2.1
Name: subdo
Version: 0.1
Summary: The easy subtitle downloader for all videos
Home-page: https://github.com/kevalvc/Video-Subtitle-Downloader
Author: Keval Chavda
Author-email: chavda.keval97@gmail.com
License: MIT
Platform: UNKNOWN
Classifier: Programming Language :: Python :: 3
Classifier: License :: OSI Approved :: MIT License
Classifier: Operating System :: OS Independent
